LICENSE
MANIFEST.in
README.md
setup.py
ziqiang/__init__.py
ziqiang/script_train.py
ziqiang/zzz_try.py
ziqiang.egg-info/PKG-INFO
ziqiang.egg-info/SOURCES.txt
ziqiang.egg-info/dependency_links.txt
ziqiang.egg-info/top_level.txt
ziqiang/agents/__init__.py
ziqiang/agents/dqn.py
ziqiang/envs/__init__.py
ziqiang/envs/grid_world.py
ziqiang/replay_buffers/__init__.py
ziqiang/replay_buffers/simple_buffer.py
ziqiang/trainers/__init__.py
ziqiang/trainers/simple_trainer.py
ziqiang/utils/__init__.py
ziqiang/utils/basic_settings.py
ziqiang/utils/multi_thread.py